keymaker/__about__.py
keymaker/__init__.py
keymaker/prompt.py
keymaker/types.py
keymaker/constraints/__init__.py
keymaker/constraints/base.py
keymaker/constraints/json.py
keymaker/constraints/logical.py
keymaker/constraints/model.py
keymaker/constraints/options.py
keymaker/constraints/parser.py
keymaker/constraints/regex.py
keymaker/constraints/stops.py
keymaker/models/__init__.py
keymaker/models/base.py
keymaker/models/huggingface.py
keymaker/models/litellm.py
keymaker/models/llama_cpp.py
keymaker/models/openai.py
keymaker/utils/__init__.py
keymaker/utils/chat.py
keymaker/utils/exceptions.py
keymaker/utils/formatted_completion.py
keymaker/utils/general.py
headjack_keymaker-0.9.4.dist-info/METADATA
headjack_keymaker-0.9.4.dist-info/WHEEL
headjack_keymaker-0.9.4.dist-info/RECORD
