Metadata-Version: 2.3
Name: headjack-keymaker
Version: 0.9.4
Summary: The most powerful, flexible and extensible way to control the output of large language models.
Project-URL: repository, https://github.com/KnowledgeForge/keymaker
Author-email: circargs <nick@ouellet.dev>, Nick Ouellet <nick@ouellet.dev>
License: Apache 2.0
Requires-Python: <4.0,>=3.8
Requires-Dist: lark>=1.1.5
Requires-Dist: openai>=1.0.0
Requires-Dist: parsy>=2.1
Requires-Dist: regex>=2023.6.3
Requires-Dist: tiktoken>=0.4.0
Provides-Extra: all
Requires-Dist: headjack-keymaker[huggingface,litellm,llamacpp]; extra == 'all'
Provides-Extra: huggingface
Requires-Dist: numpy; extra == 'huggingface'
Requires-Dist: torch; extra == 'huggingface'
Requires-Dist: transformers>=4.30.2; extra == 'huggingface'
Provides-Extra: litellm
Requires-Dist: litellm>=1.7.0; extra == 'litellm'
Provides-Extra: llamacpp
Requires-Dist: llama-cpp-python>=0.1.68; extra == 'llamacpp'
Requires-Dist: numpy; extra == 'llamacpp'
